mgcv_rust-0.4.0.dist-info/METADATA
mgcv_rust-0.4.0.dist-info/WHEEL
mgcv_rust-0.4.0.dist-info/licenses/LICENSE
mgcv_rust/__init__.py
mgcv_rust/mgcv_rust.cpython-38-x86_64-linux-gnu.so
mgcv_rust-0.4.0.dist-info/RECORD
