Metadata-Version: 2.4
Name: mgcv-rust
Version: 0.4.0
Classifier: Development Status :: 4 - Beta
Classifier: Intended Audience :: Science/Research
Classifier: License :: OSI Approved :: MIT License
Classifier: Programming Language :: Python :: 3
Classifier: Programming Language :: Python :: 3.8
Classifier: Programming Language :: Python :: 3.9
Classifier: Programming Language :: Python :: 3.10
Classifier: Programming Language :: Python :: 3.11
Classifier: Programming Language :: Python :: 3.12
Classifier: Programming Language :: Rust
Classifier: Programming Language :: Python :: Implementation :: CPython
Classifier: Topic :: Scientific/Engineering
Requires-Dist: numpy>=1.20.0
License-File: LICENSE
Summary: Rust implementation of Generalized Additive Models with Python bindings
Keywords: statistics,machine-learning,gam,regression,splines
Author-email: Aleksander Jaworski <ale.jaworski@gmail.com>
Requires-Python: >=3.8
Project-URL: Homepage, https://github.com/AlekJaworski/nn_exploring
Project-URL: Repository, https://github.com/AlekJaworski/nn_exploring
Project-URL: Issues, https://github.com/AlekJaworski/nn_exploring/issues
